brioche/__init__.py
brioche/models.py
brioche/multisetEnrichment.py
brioche/plot.py
brioche/test_n2.py
brioche_enrichment-0.1.2a0.dist-info/LICENSE
brioche_enrichment-0.1.2a0.dist-info/METADATA
brioche_enrichment-0.1.2a0.dist-info/WHEEL
brioche_enrichment-0.1.2a0.dist-info/RECORD
