Metadata-Version: 2.1
Name: brioche-enrichment
Version: 0.1.2a0
Summary: Bayesian tests for set enrichment.
License: MIT
Author: Daniel O'Hanlon
Author-email: dpohanlon@gmail.com
Requires-Python: >=3.8,<3.12
Classifier: License :: OSI Approved :: MIT License
Classifier: Programming Language :: Python :: 3
Classifier: Programming Language :: Python :: 3.8
Classifier: Programming Language :: Python :: 3.9
Classifier: Programming Language :: Python :: 3.10
Classifier: Programming Language :: Python :: 3.11
Requires-Dist: jax (>=0.4.5,<0.5.0)
Requires-Dist: matplotlib (>=3.7.0,<4.0.0)
Requires-Dist: numpy (>=1.24.2,<2.0.0)
Requires-Dist: numpyro (>=0.11.0,<0.12.0)
Requires-Dist: pandas (>=1.5.3,<2.0.0)
Requires-Dist: scipy (>=1.10.1)
Requires-Dist: seaborn (>=0.12.2,<0.13.0)
Requires-Dist: statsmodels (>=0.13.5)
Requires-Dist: tqdm (>=4.64.1,<5.0.0)
